glam_processing/__init__.py
glam_processing/cli.py
glam_processing/config/__init__.py
glam_processing/config/clms.py
glam_processing/config/settings.py
glam_processing/download.py
glam_processing/earthdata.py
glam_processing/exceptions.py
glam_processing/spectral.py
glam_processing/utils.py
glam_processing-0.4.4.dist-info/METADATA
glam_processing-0.4.4.dist-info/WHEEL
glam_processing-0.4.4.dist-info/entry_points.txt
glam_processing-0.4.4.dist-info/RECORD
